{
  "schema": "wrf_gpu2.proofs.v060.bmj_fp64_oracle_crosscheck.v1",
  "purpose": "Corroborating evidence that the JAX BMJ port is WRF-faithful: compare the fp64 JAX port to a SECOND pristine-WRF oracle built with -fdefault-real-8 (fp64). The much-tighter agreement vs the fp32 savepoints isolates the committed-savepoint residual as fp32 oracle precision, not a port defect.",
  "fp64_oracle_build": "gfortran -O2 -fdefault-real-8 -fdefault-double-8 on UNMODIFIED module_cu_bmj.F + same single-column driver",
  "cases": [
    {
      "case": "bmj_case_1",
      "regime": "deep",
      "RAINCV_jax_fp64": 0.13310600063443934,
      "RAINCV_oracle_fp64": 0.1331063765601664,
      "RAINCV_oracle_fp32_savepoint": 0.1331052631139755,
      "RAINCV_relerr_vs_fp64_oracle": 2.824250323614718e-06,
      "RAINCV_relerr_vs_fp32_savepoint": 5.540881303903232e-06,
      "RTHCUTEN_maxabs_vs_fp64_oracle": 2.1004123132613295e-08,
      "RTHCUTEN_maxabs_vs_fp32_savepoint": 8.562640930803375e-08,
      "RTHCUTEN_tol_abs": 5e-08,
      "CUTOP_jax": 31.0,
      "CUTOP_oracle": 31.0,
      "CUBOT_jax": 2.0,
      "CUBOT_oracle": 2.0
    },
    {
      "case": "bmj_case_3",
      "regime": "deep",
      "RAINCV_jax_fp64": 0.19783214638946062,
      "RAINCV_oracle_fp64": 0.1978322629663095,
      "RAINCV_oracle_fp32_savepoint": 0.1978295892477036,
      "RAINCV_relerr_vs_fp64_oracle": 5.892711691635723e-07,
      "RAINCV_relerr_vs_fp32_savepoint": 1.2925982239225852e-05,
      "RTHCUTEN_maxabs_vs_fp64_oracle": 2.774279601099744e-08,
      "RTHCUTEN_maxabs_vs_fp32_savepoint": 3.2632148039670253e-07,
      "RTHCUTEN_tol_abs": 5e-08,
      "CUTOP_jax": 35.0,
      "CUTOP_oracle": 35.0,
      "CUBOT_jax": 2.0,
      "CUBOT_oracle": 2.0
    }
  ]
}